rwx/__init__.py
rwx/__main__.py
rwx/arg/__init__.py
rwx/cmd/__init__.py
rwx/cmd/squashfs/__init__.py
rwx/deb/__init__.py
rwx/err/__init__.py
rwx/fs/__init__.py
rwx/grub/__init__.py
rwx/log/__init__.py
rwx/project/__init__.py
rwx/ps/__init__.py
rwx/txt/__init__.py
rwx-0.0.1.dist-info/METADATA
rwx-0.0.1.dist-info/WHEEL
rwx-0.0.1.dist-info/licenses/license.md
rwx-0.0.1.dist-info/RECORD
